developer_platform_client_py/__init__.py
developer_platform_client_py/block.py
developer_platform_client_py/client.py
developer_platform_client_py/contract.py
developer_platform_client_py/integrations/api_interfaces.py
developer_platform_client_py/integrations/block_api.py
developer_platform_client_py/integrations/contract_api.py
developer_platform_client_py/integrations/token_api.py
developer_platform_client_py/integrations/transaction_api.py
developer_platform_client_py/integrations/wallet_api.py
developer_platform_client_py/interfaces/chain_interfaces.py
developer_platform_client_py/token.py
developer_platform_client_py/transaction.py
developer_platform_client_py/wallet.py
developer_platform_client_py-1.0.1.dist-info/LICENSE
developer_platform_client_py-1.0.1.dist-info/METADATA
developer_platform_client_py-1.0.1.dist-info/WHEEL
developer_platform_client_py-1.0.1.dist-info/entry_points.txt
developer_platform_client_py-1.0.1.dist-info/RECORD
